{
    "configurations": [
        {
            "name": "Win32",
            "includePath": [
                "${workspaceFolder}/**"
            ],
            "defines": [
                "_DEBUG",
                "UNICODE",
                "_UNICODE"
            ],
           // "compilerPath": "C:\\Program Files\\Microsoft Visual Studio\\2022\\Professional\\VC\\Tools\\MSVC\\14.35.32215\\bin\\Hostx64\\x64\\cl.exe",
            "compilerPath": "C:\\Program Files\\CodeBlocks\\MinGW\\bin\\gcc.exe",
            "cStandard": "c17",
            "cppStandard": "c++17",
            "intelliSenseMode": "windows-gcc-x64"
        }
    ],
    "version": 4
}